shoe_sensor/__init__.py
shoe_sensor/core.py
shoe_sensor/tools/__init__.py
shoe_sensor/tools/collect_csv.py
shoe_sensor/tools/collect_honeycomb.py
shoe_sensor/tools/shoe_scan.py
wf_shoe_sensor-0.2.3.dist-info/METADATA
wf_shoe_sensor-0.2.3.dist-info/WHEEL
wf_shoe_sensor-0.2.3.dist-info/top_level.txt
wf_shoe_sensor-0.2.3.dist-info/RECORD
