Metadata-Version: 2.1
Name: wf-shoe-sensor
Version: 0.2.3
Summary: Python package for communicating with Wildflower shoe sensors through BLE interface
Home-page: https://github.com/WildflowerSchools/shoe_sensor
Author: Theodore Quinn
Author-email: ted.quinn@wildflowerschools.org
License: UNKNOWN
Keywords: bluetooth
Platform: UNKNOWN
Classifier: Intended Audience :: Developers
Classifier: License :: OSI Approved :: MIT License
Classifier: Operating System :: POSIX :: Linux
Classifier: Programming Language :: Python
Requires-Dist: wf-database-connection-honeycomb (>=0.2.1)
Requires-Dist: bluepy (>=1.3.0)
Requires-Dist: click (>=7.0)
